pytest_gee/__init__.py
pytest_gee/dictionary_regression.py
pytest_gee/feature_collection_regression.py
pytest_gee/image_regression.py
pytest_gee/list_regression.py
pytest_gee/plugin.py
pytest_gee/py.typed
pytest_gee/utils.py
pytest_gee-0.8.1.dist-info/METADATA
pytest_gee-0.8.1.dist-info/WHEEL
pytest_gee-0.8.1.dist-info/entry_points.txt
pytest_gee-0.8.1.dist-info/licenses/AUTHORS.rst
pytest_gee-0.8.1.dist-info/licenses/LICENSE
pytest_gee-0.8.1.dist-info/RECORD
