Metadata-Version: 2.4
Name: pytest-gee
Version: 0.8.1
Summary: The Python plugin for your GEE based packages.
Project-URL: Homepage, https://github.com/gee-community/pytest-gee
Author-email: Pierrick Rambaud <pierrick.rambaud49@gmail.com>
License: MIT
License-File: AUTHORS.rst
License-File: LICENSE
Keywords: Python,skeleton
Classifier: Development Status :: 3 - Alpha
Classifier: Intended Audience :: Developers
Classifier: License :: OSI Approved :: MIT License
Classifier: Programming Language :: Python :: 3.9
Classifier: Programming Language :: Python :: 3.10
Classifier: Programming Language :: Python :: 3.11
Classifier: Programming Language :: Python :: 3.12
Classifier: Programming Language :: Python :: 3.13
Requires-Python: >=3.9
Requires-Dist: deprecated>=1.2.14
Requires-Dist: earthengine-api>=0.1.397
Requires-Dist: geopandas
Requires-Dist: pillow
Requires-Dist: pytest
Requires-Dist: pytest-regressions>=2.7.0
Provides-Extra: doc
Requires-Dist: pydata-sphinx-theme; extra == 'doc'
Requires-Dist: sphinx-autoapi; extra == 'doc'
Requires-Dist: sphinx-copybutton; extra == 'doc'
Requires-Dist: sphinx-design; extra == 'doc'
Requires-Dist: sphinx<8,>=6.2.1; extra == 'doc'
Requires-Dist: sphinxemoji; extra == 'doc'
Provides-Extra: test
Requires-Dist: pytest; extra == 'test'
Requires-Dist: pytest-cov; extra == 'test'
Requires-Dist: pytest-deadfixtures; extra == 'test'
